sanic_book/__init__.py
sanic_book-0.0.1.dist-info/entry_points.txt
sanic_book-0.0.1.dist-info/LICENSE
sanic_book-0.0.1.dist-info/WHEEL
sanic_book-0.0.1.dist-info/METADATA
sanic_book-0.0.1.dist-info/RECORD
